{"Rank": 192, "FullName": "Daniel Kaluuya", "DomesticBoxOfficeRevenue": 962311173, "AverageDomesticBoxOfficeRevenue": 192462235, "DataSourceUrl": "https://www.imdb.com/find?s=nm&q=Daniel+Kaluuya&ref_=nv_sr_sm", "LocalDataSourcePath": "./html/imdb_profiles/DanielKaluuya.html", "PhotoUrl": "https://m.media-amazon.com/images/M/MV5BOTk1MzgzOTg5OV5BMl5BanBnXkFtZTcwNDQ4NjMxOA@@._V1_UY317_CR1,0,214,317_AL_.jpg", "DOB": "1989-2-24", "BornIn": "London, England, UK", "Gender": "Male", "Height": 1.74, "AstrologicalSign": "Pisces", "AwardsWins": 18, "AwardNominations": 59, "Roles": [{"CharacterName": "", "Year": "", "FilmTitle": "The Upper World", "FilmUrl": "https://www.imdb.com/title/tt12885666/?ref_=nm_flmg_act_1", "Directors": [], "Writers": ["Femi Fadugba"], "Stars": ["Daniel Kaluuya"], "Genres": [], "ProductionCompanies": [], "PlotKeywords": []}, {"Year": "2020/II", "FilmTitle": "A Christmas Carol", "FilmUrl": "https://www.imdb.com/title/tt9136058/?ref_=nm_flmg_act_2", "Directors": ["Jacqui Morris"], "Writers": ["Charles Dickens", "David Morris"], "Stars": ["Carey Mulligan", "Martin Freeman", "Andy Serkis"], "Genres": ["Animation", "Drama"], "ProductionCompanies": ["Frith Street Films"], "PlotKeywords": ["children"], "ReleaseDate": "20 November 2020"}, {"CharacterName": "Fred Hampton", "Year": "2021", "FilmTitle": "Judas and the Black Messiah", "FilmUrl": "https://www.imdb.com/title/tt9784798/?ref_=nm_flmg_act_3", "Directors": ["Shaka King"], "Writers": ["Will Berson", "Shaka King"], "Stars": ["Daniel Kaluuya", "LaKeith Stanfield", "Jesse Plemons"], "Genres": ["Biography", "Drama", "History"], "ProductionCompanies": ["Bron Creative", "MACRO", "Participant"], "PlotKeywords": ["life", "woke", "communism"], "Popularity": 935, "MotionPictureRating": "Rated R for violence and pervasive language"}, {"CharacterName": "Jay", "Year": "2020", "FilmTitle": "Two Single Beds", "FilmUrl": "https://www.imdb.com/title/tt12635304/?ref_=nm_flmg_act_4", "Directors": ["William Stefan Smith"], "Writers": [], "Stars": ["Daniel Kaluuya", "Seraphina Beh", "Christopher York"], "Genres": ["Short", "Comedy"], "ProductionCompanies": ["59%"], "PlotKeywords": ["standup"], "ReleaseDate": "7 October 2020", "Budget": 50000, "RuntimeMinutes": 16}, {"CharacterName": "Slim", "Year": "2019", "FilmTitle": "Queen & Slim", "FilmUrl": "https://www.imdb.com/title/tt8722346/?ref_=nm_flmg_act_5", "Directors": ["Melina Matsoukas"], "Writers": ["Lena Waithe", "James Frey"], "Stars": ["Daniel Kaluuya", "Jodie Turner-Smith", "Bokeem Woodbine"], "Genres": ["Crime", "Drama", "Romance"], "ProductionCompanies": ["BRON Studios", "3Blackdot", "Creative Wealth Media Finance"], "PlotKeywords": ["title directed by female", "police officer killed", "racist cop", "road movie", "police shooting"], "Metascore": 74, "UserReviews": 347, "CriticReviews": 165, "Popularity": 733, "MotionPictureRating": "Rated R for violence, some strong sexuality, nudity, pervasive language, and brief drug use.", "ReleaseDate": "27 November 2019", "Budget": 18000000, "OpeningWeekend": 11890490, "Gross": 43808310, "CumulativeWorldwideGross": 47802566, "RuntimeMinutes": 132}, {"CharacterName": "Bluebell", "Year": "2018", "FilmTitle": "Watership Down", "FilmUrl": "https://www.imdb.com/title/tt5670764/?ref_=nm_flmg_act_6", "Directors": [], "Writers": [], "Stars": ["James McAvoy", "Nicholas Hoult", "John Boyega"], "Genres": ["Animation", "Action", "Adventure", "Drama", "Family", "Fantasy"], "ProductionCompanies": ["42", "Biscuit Filmworks", "ITV Studios Global Entertainment"], "PlotKeywords": ["netflix production", "tyranny", "visions", "beast fable", "computer animation"], "UserReviews": 169, "CriticReviews": 13, "Popularity": 735, "ReleaseDate": "23 December 2018", "RuntimeMinutes": 204}, {"CharacterName": "Jatemme Manning", "Year": "2018", "FilmTitle": "Widows", "FilmUrl": "https://www.imdb.com/title/tt4218572/?ref_=nm_flmg_act_7", "Directors": ["Steve McQueen"], "Writers": ["Gillian Flynn", "Steve McQueen"], "Stars": ["Viola Davis", "Michelle Rodriguez", "Elizabeth Debicki"], "Genres": ["Crime", "Drama", "Thriller"], "ProductionCompanies": ["New Regency Productions", "See-Saw Films", "Film4"], "PlotKeywords": ["heist", "car chase", "harlot", "based on tv series", "politician"], "Metascore": 84, "UserReviews": 589, "CriticReviews": 354, "Popularity": 549, "MotionPictureRating": "Rated R for violence, language throughout, and some sexual content/nudity", "ReleaseDate": "16 November 2018", "Budget": 42000000, "OpeningWeekend": 12361307, "Gross": 42402632, "CumulativeWorldwideGross": 75984700, "RuntimeMinutes": 129}, {"CharacterName": "W'Kabi", "Year": "2018", "FilmTitle": "Black Panther", "FilmUrl": "https://www.imdb.com/title/tt1825683/?ref_=nm_flmg_act_8", "Directors": ["Ryan Coogler"], "Writers": ["Ryan Coogler", "Joe Robert Cole"], "Stars": ["Chadwick Boseman", "Michael B. Jordan", "Lupita Nyong'o"], "Genres": ["Action", "Adventure", "Sci-Fi"], "ProductionCompanies": ["Marvel Studios", "Walt Disney Pictures"], "PlotKeywords": ["marvel cinematic universe", "marvel comics", "based on comic book", "king", "african king"], "Metascore": 88, "UserReviews": 3265, "CriticReviews": 688, "Popularity": 144, "MotionPictureRating": "Rated PG-13 for prolonged sequences of action violence, and a brief rude gesture", "ReleaseDate": "16 February 2018", "Budget": 200000000, "OpeningWeekend": 202003951, "Gross": 700426566, "CumulativeWorldwideGross": 1347426487, "RuntimeMinutes": 134}, {"CharacterName": "The Psycho Killer", "Year": "2017", "FilmTitle": "Great Performers: Horror Show", "FilmUrl": "https://www.imdb.com/title/tt8199834/?ref_=nm_flmg_act_9", "Directors": ["Floria Sigismondi"], "Writers": [], "Stars": ["Timoth\u00e9e Chalamet", "Jake Gyllenhaal", "Tiffany Haddish"], "Genres": ["Short", "Horror"], "ProductionCompanies": [], "PlotKeywords": [], "UserReviews": 2, "ReleaseDate": "7 December 2017", "RuntimeMinutes": 10}, {"CharacterName": "The Man", "Year": "2017", "FilmTitle": "Robot & Scarecrow", "FilmUrl": "https://www.imdb.com/title/tt4460802/?ref_=nm_flmg_act_10", "Directors": ["Kibwe Tavares"], "Writers": ["Christopher O'Reilly", "Ursula Rani Sarma"], "Stars": ["Jack O'Connell", "Holliday Grainger", "Daniel Kaluuya"], "Genres": ["Short", "Romance", "Sci-Fi"], "ProductionCompanies": ["DMC Film", "Factory Fifteen", "Nexus Studios"], "PlotKeywords": [], "UserReviews": 4, "CriticReviews": 2, "ReleaseDate": "4 June 2017", "RuntimeMinutes": 15}, {"CharacterName": "Chris Washington", "Year": "2017/I", "FilmTitle": "Get Out", "FilmUrl": "https://www.imdb.com/title/tt5052448/?ref_=nm_flmg_act_11", "Directors": ["Jordan Peele"], "Writers": ["Jordan Peele"], "Stars": ["Daniel Kaluuya", "Allison Williams", "Bradley Whitford"], "Genres": ["Horror", "Mystery", "Thriller"], "ProductionCompanies": ["Universal Pictures", "Blumhouse Productions", "QC Entertainment"], "PlotKeywords": ["hypnosis", "racism", "neurosurgeon", "abduction", "brain surgery"], "Metascore": 85, "UserReviews": 1611, "CriticReviews": 736, "Popularity": 182, "MotionPictureRating": "Rated R for violence, bloody images, and language including sexual references", "ReleaseDate": "24 February 2017", "Budget": 4500000, "OpeningWeekend": 33377060, "Gross": 176040665, "CumulativeWorldwideGross": 255429395, "RuntimeMinutes": 104}, {"CharacterName": "Reggie Wayne", "Year": "2015", "FilmTitle": "Sicario", "FilmUrl": "https://www.imdb.com/title/tt3397884/?ref_=nm_flmg_act_12", "Directors": ["Denis Villeneuve"], "Writers": ["Taylor Sheridan"], "Stars": ["Emily Blunt", "Josh Brolin", "Benicio Del Toro"], "Genres": ["Action", "Crime", "Drama", "Mystery", "Thriller"], "ProductionCompanies": ["Lionsgate", "Black Label Media", "Thunder Road Pictures"], "PlotKeywords": ["war on drugs", "drug cartel", "juarez mexico", "neo noir", "surprise ending"], "Metascore": 82, "UserReviews": 733, "CriticReviews": 545, "Popularity": 499, "MotionPictureRating": "Rated R for strong violence, grisly images, and language", "ReleaseDate": "2 October 2015", "Budget": 30000000, "OpeningWeekend": 401288, "Gross": 46889293, "CumulativeWorldwideGross": 84872444, "RuntimeMinutes": 121}, {"CharacterName": "Matt Coward", "Year": "2014", "FilmTitle": "Babylon", "FilmUrl": "https://www.imdb.com/title/tt3138900/?ref_=nm_flmg_act_13", "Directors": ["Damien Chazelle"], "Writers": ["Damien Chazelle"], "Stars": ["Brad Pitt", "Emma Stone", "Tobey Maguire"], "Genres": ["Drama"], "ProductionCompanies": ["Marc Platt Productions", "Material Pictures", "Paramount Pictures"], "PlotKeywords": [], "Popularity": 388, "ReleaseDate": "25 December 2021"}, {"CharacterName": "Dave", "Year": "2014/II", "FilmTitle": "Date Night", "FilmUrl": "https://www.imdb.com/title/tt3562082/?ref_=nm_flmg_act_14", "Directors": ["Shawn Levy"], "Writers": ["Josh Klausner"], "Stars": ["Steve Carell", "Tina Fey", "Mark Wahlberg"], "Genres": ["Comedy", "Crime", "Romance", "Thriller"], "ProductionCompanies": ["Twentieth Century Fox", "21 Laps Entertainment", "Dune Entertainment"], "PlotKeywords": ["downtown", "desire", "thug", "criminal", "kingpin"], "Metascore": 56, "UserReviews": 234, "CriticReviews": 262, "Popularity": 929, "MotionPictureRating": "Rated PG-13 for sexual and crude content throughout, language, some violence and a drug reference", "ReleaseDate": "9 April 2010", "Budget": 55000000, "OpeningWeekend": 25207599, "Gross": 98711404, "CumulativeWorldwideGross": 152263880, "RuntimeMinutes": 88}, {"CharacterName": "Black Death", "Year": "2013", "FilmTitle": "Kick-Ass 2", "FilmUrl": "https://www.imdb.com/title/tt1650554/?ref_=nm_flmg_act_15", "Directors": ["Jeff Wadlow"], "Writers": ["Jeff Wadlow", "Mark Millar"], "Stars": ["Aaron Taylor-Johnson", "Chlo\u00eb Grace Moretz", "Christopher Mintz-Plasse"], "Genres": ["Action", "Comedy", "Crime", "Thriller"], "ProductionCompanies": ["Universal Pictures", "Marv Films", "Dentsu"], "PlotKeywords": ["superhero", "high school", "vigilante", "kicked in the crotch", "punched in the crotch"], "Metascore": 41, "UserReviews": 400, "CriticReviews": 359, "Popularity": 790, "MotionPictureRating": "Rated R for strong violence, pervasive language, crude and sexual content, and brief nudity", "ReleaseDate": "16 August 2013", "Budget": 28000000, "OpeningWeekend": 13332955, "Gross": 28795985, "CumulativeWorldwideGross": 60795985, "RuntimeMinutes": 103}, {"CharacterName": "Juka Ogadowa", "Year": "2013", "FilmTitle": "Welcome to the Punch", "FilmUrl": "https://www.imdb.com/title/tt1684233/?ref_=nm_flmg_act_16", "Directors": ["Eran Creevy"], "Writers": ["Eran Creevy"], "Stars": ["James McAvoy", "Mark Strong", "Andrea Riseborough"], "Genres": ["Action", "Crime", "Thriller"], "ProductionCompanies": ["Worldview Entertainment", "Between The Eyes", "Automatik Entertainment"], "PlotKeywords": ["suspense", "detective", "heist", "conspiracy", "criminal"], "Metascore": 49, "UserReviews": 92, "CriticReviews": 129, "MotionPictureRating": "Rated R for violence and language", "ReleaseDate": "15 March 2013", "Budget": 8500000, "OpeningWeekend": 2736, "Gross": 9747, "CumulativeWorldwideGross": 3926386, "RuntimeMinutes": 99}, {"CharacterName": "Mbwana", "Year": "2013/II", "FilmTitle": "Jonah", "FilmUrl": "https://www.imdb.com/title/tt2690924/?ref_=nm_flmg_act_17", "Directors": ["Kibwe Tavares"], "Writers": ["Jack Thorne"], "Stars": ["Daniel Kaluuya", "Malachi Kirby", "Louis Mahoney"], "Genres": ["Short", "Drama", "Fantasy"], "ProductionCompanies": ["BFI Film Fund", "Factory Fifteen"], "PlotKeywords": [], "UserReviews": 5, "CriticReviews": 1, "ReleaseDate": "16 January 2013", "RuntimeMinutes": 17}, {"CharacterName": "Stanley", "Year": "2012", "FilmTitle": "Beginning", "FilmUrl": "https://www.imdb.com/title/tt2398720/?ref_=nm_flmg_act_18", "Directors": ["Pier Wilkie"], "Writers": ["Pier Wilkie"], "Stars": ["Daniel Kaluuya", "Luke Kidd", "Vinette Robinson"], "Genres": ["Short", "Drama"], "ProductionCompanies": [], "PlotKeywords": [], "RuntimeMinutes": 19}, {"CharacterName": "Parking Pataweyo", "Year": "2010-2012", "FilmTitle": "Ruddy Hell! It's Harry and Paul", "FilmUrl": "https://www.imdb.com/title/tt0976015/?ref_=nm_flmg_act_19", "Directors": [], "Writers": [], "Stars": ["Harry Enfield", "Paul Whitehouse", "Sophie Winkleman"], "Genres": ["Comedy"], "ProductionCompanies": ["Tiger Aspect Productions"], "PlotKeywords": ["alternative comedy", "british comedy", "sketch comedy", "comedy sketch"], "UserReviews": 7, "ReleaseDate": "13 April 2007", "RuntimeMinutes": 30}, {"CharacterName": "Bingham 'Bing' Madsen", "Year": "2011", "FilmTitle": "Black Mirror", "FilmUrl": "https://www.imdb.com/title/tt2085059/?ref_=nm_flmg_act_20", "Directors": [], "Writers": [], "Stars": ["Daniel Lapaine", "Hannah John-Kamen", "Michaela Coel"], "Genres": ["Drama", "Sci-Fi", "Thriller"], "ProductionCompanies": ["Zeppotron", "Channel 4 Television Corporation", "Gran Babieka"], "PlotKeywords": ["anthology", "satire", "dystopian future", "dystopia", "netflix original"], "UserReviews": 739, "CriticReviews": 101, "Popularity": 61, "ReleaseDate": "4 December 2011", "CumulativeWorldwideGross": 320000, "RuntimeMinutes": 60}, {"CharacterName": "Mac", "Year": "2011", "FilmTitle": "The Fades", "FilmUrl": "https://www.imdb.com/title/tt1772379/?ref_=nm_flmg_act_21", "Directors": [], "Writers": [], "Stars": ["Lily Loveless", "Tom Ellis", "Daniel Kaluuya"], "Genres": ["Fantasy", "Horror", "Mystery"], "ProductionCompanies": ["British Broadcasting Corporation (BBC) Television"], "PlotKeywords": ["tv mini series", "supernatural power"], "UserReviews": 26, "CriticReviews": 10, "Popularity": 277}, {"CharacterName": "Agent Tucker", "Year": "2011", "FilmTitle": "Johnny English Reborn", "FilmUrl": "https://www.imdb.com/title/tt1634122/?ref_=nm_flmg_act_22", "Directors": ["Oliver Parker"], "Writers": ["Hamish McColl", "William Davies"], "Stars": ["Rowan Atkinson", "Rosamund Pike", "Dominic West"], "Genres": ["Action", "Adventure", "Comedy"], "ProductionCompanies": ["Universal Pictures", "Relativity Media", "StudioCanal"], "PlotKeywords": ["based on commercial", "murderess", "men's room", "fainting man", "martial arts school"], "Metascore": 46, "UserReviews": 184, "CriticReviews": 162, "Popularity": 391, "MotionPictureRating": "Rated PG for mild action violence, rude humor, some language and brief sensuality.", "ReleaseDate": "21 October 2011", "Budget": 45000000, "OpeningWeekend": 3833300, "Gross": 8305970, "CumulativeWorldwideGross": 160078586, "RuntimeMinutes": 101}, {"CharacterName": "Brother", "Year": "2011", "FilmTitle": "Random", "FilmUrl": "https://www.imdb.com/title/tt2004332/?ref_=nm_flmg_act_23", "Directors": ["Debbie Tucker Green"], "Writers": ["Debbie Tucker Green"], "Stars": ["Nadine Marshall", "Daniel Kaluuya", "Jay Byrd"], "Genres": ["Drama"], "ProductionCompanies": ["Hillbilly Films"], "PlotKeywords": [], "UserReviews": 2, "CriticReviews": 1, "ReleaseDate": "23 August 2011"}, {"CharacterName": "Micah", "Year": "2011", "FilmTitle": "Coming Up", "FilmUrl": "https://www.imdb.com/title/tt0406404/?ref_=nm_flmg_act_24", "Directors": [], "Writers": [], "Stars": ["Fotios Foddy Savva", "Johnny Harris", "Anthony Flanagan"], "Genres": ["Drama"], "ProductionCompanies": ["Ideal World Productions", "Touchpaper Television"], "PlotKeywords": ["writer"], "UserReviews": 3, "ReleaseDate": "20 August 2003", "Budget": 100000}, {"CharacterName": "Tealeaf / Michael / Michael Fry", "Year": "2009-2011", "FilmTitle": "Psychoville", "FilmUrl": "https://www.imdb.com/title/tt1305562/?ref_=nm_flmg_act_25", "Directors": [], "Writers": [], "Stars": ["Reece Shearsmith", "Steve Pemberton", "Daniel Kaluuya"], "Genres": ["Comedy", "Horror", "Mystery"], "ProductionCompanies": ["British Broadcasting Corporation (BBC)"], "PlotKeywords": ["psychotronic series", "character credited as self", "sitcom", "absurd humor", "absurdism"], "UserReviews": 18, "CriticReviews": 5, "Popularity": 795, "ReleaseDate": "18 June 2009", "RuntimeMinutes": 30}, {"CharacterName": "Damon", "Year": "2010/II", "FilmTitle": "Baby", "FilmUrl": "https://www.imdb.com/title/tt1772761/?ref_=nm_flmg_act_26", "Directors": ["Daniel Mulloy"], "Writers": ["Daniel Mulloy"], "Stars": ["Arta Dobroshi", "Daniel Kaluuya", "Etela Pardo"], "Genres": ["Short", "Drama"], "ProductionCompanies": ["Sister Films"], "PlotKeywords": ["woman", "black man white woman romance", "black man white woman sex", "black man white woman kiss", "black man white woman relationship"], "UserReviews": 2, "CriticReviews": 3, "ReleaseDate": "1 April 2011", "Budget": 50000, "RuntimeMinutes": 25}, {"CharacterName": "Mo", "Year": "2010", "FilmTitle": "Chatroom", "FilmUrl": "https://www.imdb.com/title/tt1319704/?ref_=nm_flmg_act_27", "Directors": ["Hideo Nakata"], "Writers": ["Enda Walsh"], "Stars": ["Jacob Anderson", "Matthew Ashforde", "Dorothy Atkinson"], "Genres": ["Drama", "Thriller"], "ProductionCompanies": ["Ruby Films", "Film4", "UK Film Council"], "PlotKeywords": ["self injury", "depression", "teenager", "friendship", "mother son relationship"], "UserReviews": 48, "CriticReviews": 67, "MotionPictureRating": "Rated R for disturbing violent content, some sexual material and brief language", "ReleaseDate": "22 December 2010", "CumulativeWorldwideGross": 683912, "RuntimeMinutes": 97}, {"CharacterName": "Various", "Year": "2010", "FilmTitle": "Comedy Lab", "FilmUrl": "https://www.imdb.com/title/tt0178131/?ref_=nm_flmg_act_28", "Directors": [], "Writers": [], "Stars": ["Tom Meeten", "Alice Lowe", "Simon Greenall"], "Genres": ["Comedy"], "ProductionCompanies": ["Room 5"], "PlotKeywords": ["slapstick comedy", "british comedy", "sketch comedy", "stand up comedy"], "ReleaseDate": "9 November 1998", "Budget": 70000, "RuntimeMinutes": 25}, {"CharacterName": "Various", "Year": "2010", "FilmTitle": "Bellamy's People", "FilmUrl": "https://www.imdb.com/title/tt1581696/?ref_=nm_flmg_act_29", "Directors": [], "Writers": [], "Stars": ["Rhys Thomas", "Simon Day", "Felix Dexter"], "Genres": ["Comedy"], "ProductionCompanies": ["BBC Vision Productions", "Down the Line Productions", "Marmalade Studios"], "PlotKeywords": ["spoof", "radio personality"], "UserReviews": 1, "CriticReviews": 1, "ReleaseDate": "21 January 2010", "RuntimeMinutes": 30}, {"CharacterName": "Solider 2", "Year": "2009", "FilmTitle": "10 Minute Tales", "FilmUrl": "https://www.imdb.com/title/tt1574452/?ref_=nm_flmg_act_30", "Directors": [], "Writers": [], "Stars": ["Peter Capaldi", "Mackenzie Crook", "Hunter the Dog"], "Genres": ["Comedy", "Drama"], "ProductionCompanies": ["Endor Productions", "British Sky Broadcasting (BSkyB)"], "PlotKeywords": ["short story", "number in title"], "UserReviews": 1, "CriticReviews": 1, "ReleaseDate": "21 December 2009"}, {"CharacterName": "", "Year": "2009", "FilmTitle": "The Philanthropist", "FilmUrl": "https://www.imdb.com/title/tt1217208/?ref_=nm_flmg_act_31", "Directors": [], "Writers": [], "Stars": ["James Purefoy", "Neve Campbell", "Michael Kenneth Williams"], "Genres": ["Action", "Adventure", "Drama"], "ProductionCompanies": ["Carnival Film & Television", "Stillking Films", "The Levinson / Fontana Company"], "PlotKeywords": [], "UserReviews": 20, "CriticReviews": 5}, {"CharacterName": "Various / Poor Black Kid", "Year": "2008-2009", "FilmTitle": "That Mitchell and Webb Look", "FilmUrl": "https://www.imdb.com/title/tt0499410/?ref_=nm_flmg_act_32", "Directors": [], "Writers": [], "Stars": ["David Mitchell", "Robert Webb", "James Bachman"], "Genres": ["Comedy", "Fantasy"], "ProductionCompanies": ["British Broadcasting Corporation (BBC)"], "PlotKeywords": ["social satire", "satire", "parody", "crazy humor", "absurdism"], "UserReviews": 5, "CriticReviews": 5, "RuntimeMinutes": 720}, {"CharacterName": "", "Year": "2009", "FilmTitle": "Brink", "FilmUrl": "https://www.imdb.com/title/tt2606624/?ref_=nm_flmg_act_33", "Directors": ["Philip Goldie"], "Writers": ["Daniel Lovett"], "Stars": ["Max Fowler", "Daniel Kaluuya", "Gemma Salusbury"], "Genres": ["Short", "Drama"], "ProductionCompanies": ["Company Pictures"], "PlotKeywords": [], "ReleaseDate": "30 June 2009", "RuntimeMinutes": 14}, {"CharacterName": "Barclay", "Year": "2009", "FilmTitle": "Doctor Who", "FilmUrl": "https://www.imdb.com/title/tt0436992/?ref_=nm_flmg_act_34", "Directors": [], "Writers": [], "Stars": ["Jodie Whittaker", "Peter Capaldi", "Pearl Mackie"], "Genres": ["Adventure", "Drama", "Family", "Mystery", "Sci-Fi"], "ProductionCompanies": ["BBC Wales", "British Broadcasting Corporation (BBC)", "Canadian Broadcasting Corporation (CBC)"], "PlotKeywords": ["time travel", "time machine", "alien", "space travel", "companion"], "UserReviews": 795, "CriticReviews": 212, "Popularity": 77, "ReleaseDate": "17 March 2006", "OpeningWeekend": 228615, "Gross": 76205, "CumulativeWorldwideGross": 76205, "RuntimeMinutes": 45}, {"CharacterName": "Ades", "Year": "2009", "FilmTitle": "FM", "FilmUrl": "https://www.imdb.com/title/tt1385167/?ref_=nm_flmg_act_35", "Directors": [], "Writers": [], "Stars": ["Chris O'Dowd", "Kevin Bishop", "Nina Sosanya"], "Genres": ["Comedy"], "ProductionCompanies": ["Granada Television", "ITV Productions"], "PlotKeywords": [], "UserReviews": 1, "ReleaseDate": "25 February 2009"}, {"CharacterName": "Declan", "Year": "2009", "FilmTitle": "Inspector Lewis", "FilmUrl": "https://www.imdb.com/title/tt0874608/?ref_=nm_flmg_act_36", "Directors": [], "Writers": [], "Stars": ["Kevin Whately", "Laurence Fox", "Clare Holman"], "Genres": ["Crime", "Drama", "Mystery"], "ProductionCompanies": ["Granada Media", "Granada Television", "ITV Productions"], "PlotKeywords": ["sequel", "buddy", "buddy cop", "character name as series title", "detective sergeant"], "UserReviews": 33, "CriticReviews": 18, "Popularity": 505, "ReleaseDate": "30 July 2006", "RuntimeMinutes": 90}, {"CharacterName": "Dan", "Year": "2009", "FilmTitle": "Not Safe for Work", "FilmUrl": "https://www.imdb.com/title/tt1552204/?ref_=nm_flmg_act_37", "Directors": ["Misha Manson-Smith"], "Writers": ["Mike O'Leary", "Ben Schiffer"], "Stars": ["William Andrews", "Antonia Campbell-Hughes", "Daniella Dessa"], "Genres": ["Short", "Comedy", "Drama"], "ProductionCompanies": ["National Film and Television School (NFTS)", "Company Pictures"], "PlotKeywords": [], "ReleaseDate": "3 March 2009"}, {"CharacterName": "Posh Kenneth", "Year": "2007-2009", "FilmTitle": "Skins", "FilmUrl": "https://www.imdb.com/title/tt0840196/?ref_=nm_flmg_act_38", "Directors": [], "Writers": [], "Stars": ["Kaya Scodelario", "Nicholas Hoult", "Joe Dempsie"], "Genres": ["Drama"], "ProductionCompanies": ["Company Pictures", "E4", "Stormdog Films"], "PlotKeywords": ["bristol england", "teenage boy", "friendship", "college", "friendship between girls"], "UserReviews": 123, "CriticReviews": 22, "Popularity": 446, "ReleaseDate": "17 January 2011"}, {"CharacterName": "Errol Harris", "Year": "2008", "FilmTitle": "Silent Witness", "FilmUrl": "https://www.imdb.com/title/tt0115355/?ref_=nm_flmg_act_39", "Directors": [], "Writers": [], "Stars": ["Emilia Fox", "William Gaminara", "Tom Ward"], "Genres": ["Crime", "Drama", "Mystery"], "ProductionCompanies": ["British Broadcasting Corporation (BBC)", "A+E Networks", "Cipango Productions Audiovisuelles"], "PlotKeywords": ["caucasian", "pubic hair", "naked corpse", "nylon leg", "forensics"], "UserReviews": 68, "CriticReviews": 2, "Popularity": 438, "ReleaseDate": "21 February 1996", "Budget": 7000000, "RuntimeMinutes": 60}, {"CharacterName": "Youth", "Year": "2008", "FilmTitle": "The Jason Lewis Experience", "FilmUrl": "https://www.imdb.com/title/tt1503782/?ref_=nm_flmg_act_40", "Directors": ["Jamie Cox"], "Writers": ["Jason Lewis"], "Stars": ["Jason Lewis", "Tony Cook", "Eddie Kadi"], "Genres": ["Short", "Comedy"], "ProductionCompanies": [], "PlotKeywords": [], "ReleaseDate": "1 September 2008", "Budget": 2000, "RuntimeMinutes": 30}, {"CharacterName": "Young Cass - age 14", "Year": "2008", "FilmTitle": "Cass", "FilmUrl": "https://www.imdb.com/title/tt0954981/?ref_=nm_flmg_act_41", "Directors": ["Jon S. Baird"], "Writers": ["Jon S. Baird", "Cass Pennant"], "Stars": ["Nonso Anozie", "Gavin Brocker", "Leo Gregory"], "Genres": ["Biography", "Crime", "Drama"], "ProductionCompanies": ["Cass Films", "Logie Pictures"], "PlotKeywords": ["character name as title", "jamaican", "bullying", "violence", "forename as title"], "UserReviews": 24, "CriticReviews": 21, "ReleaseDate": "1 August 2008", "Budget": 1000000, "CumulativeWorldwideGross": 241369, "RuntimeMinutes": 108}, {"CharacterName": "Roger", "Year": "2008", "FilmTitle": "Delta Forever", "FilmUrl": "https://www.imdb.com/title/tt1235487/?ref_=nm_flmg_act_42", "Directors": [], "Writers": [], "Stars": ["Samantha Blakey", "Antonia Campbell-Hughes", "Daniel Kaluuya"], "Genres": ["Comedy"], "ProductionCompanies": [], "PlotKeywords": [], "ReleaseDate": "19 May 2008"}, {"CharacterName": "Dean", "Year": "2007", "FilmTitle": "Comedy: Shuffle", "FilmUrl": "https://www.imdb.com/title/tt0908201/?ref_=nm_flmg_act_43", "Directors": [], "Writers": [], "Stars": ["Fergus Craig", "Colin Hoult", "Anna Crilly"], "Genres": ["Comedy"], "ProductionCompanies": ["British Broadcasting Corporation (BBC)"], "PlotKeywords": []}, {"CharacterName": "Shocker", "Year": "2007", "FilmTitle": "Much Ado About a Minor Ting", "FilmUrl": "https://www.imdb.com/title/tt1133940/?ref_=nm_flmg_act_44", "Directors": ["Jesse Lawrence"], "Writers": ["Jesse Lawrence", "Cristian Solimeno"], "Stars": ["Bronson Webb", "Anwar Lynch", "Daniel Kaluuya"], "Genres": ["Short", "Drama"], "ProductionCompanies": ["Film Four", "La Famiglia (I)", "UK Film Council"], "PlotKeywords": [], "ReleaseDate": "23 November 2007", "Budget": 50000, "RuntimeMinutes": 23}, {"CharacterName": "School Bully", "Year": "2007", "FilmTitle": "The Whistleblowers", "FilmUrl": "https://www.imdb.com/title/tt1030744/?ref_=nm_flmg_act_45", "Directors": [], "Writers": [], "Stars": ["Richard Coyle", "Indira Varma", "Daniel Ryan"], "Genres": ["Drama"], "ProductionCompanies": ["Carnival Film & Television"], "PlotKeywords": ["witness"], "UserReviews": 4, "ReleaseDate": "27 September 2007"}, {"CharacterName": "Reece", "Year": "2006", "FilmTitle": "Shoot the Messenger", "FilmUrl": "https://www.imdb.com/title/tt0800199/?ref_=nm_flmg_act_46", "Directors": ["Ngozi Onwurah"], "Writers": ["Sharon Foster"], "Stars": ["Medina Aijikawo", "Nikki Amuka-Bird", "Jotham Annan"], "Genres": ["Drama"], "ProductionCompanies": ["BBC Films"], "PlotKeywords": ["f rated"], "UserReviews": 27, "CriticReviews": 5, "ReleaseDate": "26 April 2006"}, {"CharacterName": "", "Year": "2011", "FilmTitle": "The Swarm", "FilmUrl": "https://www.imdb.com/title/tt2130278/?ref_=nm_flmg_wr_1", "Directors": ["Irwin Allen"], "Writers": ["Arthur Herzog III", "Stirling Silliphant"], "Stars": ["Michael Caine", "Katharine Ross", "Richard Widmark"], "Genres": ["Horror", "Thriller"], "ProductionCompanies": ["Warner Bros."], "PlotKeywords": ["swarm", "self experimentation", "english", "man wears eyeglasses", "aerial camera shot"], "Metascore": 30, "UserReviews": 138, "CriticReviews": 75, "ReleaseDate": "14 July 1978", "Budget": 21000000, "RuntimeMinutes": 116}, {"CharacterName": "", "Year": "2008-2009", "FilmTitle": "Skins", "FilmUrl": "https://www.imdb.com/title/tt0840196/?ref_=nm_flmg_wr_2", "Directors": [], "Writers": [], "Stars": ["Kaya Scodelario", "Nicholas Hoult", "Joe Dempsie"], "Genres": ["Drama"], "ProductionCompanies": ["Company Pictures", "E4", "Stormdog Films"], "PlotKeywords": ["bristol england", "teenage boy", "friendship", "college", "friendship between girls"], "UserReviews": 123, "CriticReviews": 22, "Popularity": 446, "ReleaseDate": "17 January 2011"}, {"CharacterName": "", "Year": "", "FilmTitle": "The Upper World", "FilmUrl": "https://www.imdb.com/title/tt12885666/?ref_=nm_flmg_prd_1", "Directors": [], "Writers": ["Femi Fadugba"], "Stars": ["Daniel Kaluuya"], "Genres": [], "ProductionCompanies": [], "PlotKeywords": []}, {"CharacterName": "", "Year": "2019", "FilmTitle": "Queen & Slim", "FilmUrl": "https://www.imdb.com/title/tt8722346/?ref_=nm_flmg_prd_2", "Directors": ["Melina Matsoukas"], "Writers": ["Lena Waithe", "James Frey"], "Stars": ["Daniel Kaluuya", "Jodie Turner-Smith", "Bokeem Woodbine"], "Genres": ["Crime", "Drama", "Romance"], "ProductionCompanies": ["BRON Studios", "3Blackdot", "Creative Wealth Media Finance"], "PlotKeywords": ["title directed by female", "police officer killed", "racist cop", "road movie", "police shooting"], "Metascore": 74, "UserReviews": 347, "CriticReviews": 165, "Popularity": 733, "MotionPictureRating": "Rated R for violence, some strong sexuality, nudity, pervasive language, and brief drug use.", "ReleaseDate": "27 November 2019", "Budget": 18000000, "OpeningWeekend": 11890490, "Gross": 43808310, "CumulativeWorldwideGross": 47802566, "RuntimeMinutes": 132}, {"CharacterName": "", "Year": "2011", "FilmTitle": "Skins", "FilmUrl": "https://www.imdb.com/title/tt1755893/?ref_=_1", "Directors": [], "Writers": [], "Stars": ["Kaya Scodelario", "Nicholas Hoult", "Joe Dempsie"], "Genres": ["Drama"], "ProductionCompanies": ["Company Pictures", "E4", "Stormdog Films"], "PlotKeywords": ["bristol england", "teenage boy", "friendship", "college", "friendship between girls"], "UserReviews": 123, "CriticReviews": 22, "Popularity": 446, "ReleaseDate": "17 January 2011"}, {"CharacterName": "", "Year": "2008", "FilmTitle": "Skins", "FilmUrl": "https://www.imdb.com/title/tt0840196/?ref_=_2", "Directors": [], "Writers": [], "Stars": ["Kaya Scodelario", "Nicholas Hoult", "Joe Dempsie"], "Genres": ["Drama"], "ProductionCompanies": ["Company Pictures", "E4", "Stormdog Films"], "PlotKeywords": ["bristol england", "teenage boy", "friendship", "college", "friendship between girls"], "UserReviews": 123, "CriticReviews": 22, "Popularity": 446, "ReleaseDate": "17 January 2011"}, {"CharacterName": "", "Year": "2016", "FilmTitle": "Sicario: Blunt, Brolin & Benicio - Portraying the Characters of Sicario", "FilmUrl": "https://www.imdb.com/title/tt5351462/?ref_=nm_flmg_tk_1", "Directors": [], "Writers": [], "Stars": ["Emily Blunt", "Denis Villeneuve", "Basil Iwanyk"], "Genres": ["Documentary", "Short", "Action"], "ProductionCompanies": ["Rolling Thunder Productions"], "PlotKeywords": [], "ReleaseDate": "5 January 2016", "RuntimeMinutes": 15}, {"CharacterName": "", "Year": "2016", "FilmTitle": "Stepping Into Darkness: The Visual Design of Sicario", "FilmUrl": "https://www.imdb.com/title/tt5351508/?ref_=nm_flmg_tk_2", "Directors": [], "Writers": [], "Stars": ["Denis Villeneuve", "Taylor Sheridan", "Roger Deakins"], "Genres": ["Documentary", "Short"], "ProductionCompanies": ["Rolling Thunder Productions"], "PlotKeywords": ["dvd extra"], "ReleaseDate": "5 January 2016", "RuntimeMinutes": 16}, {"CharacterName": "Self", "Year": "2019-2020", "FilmTitle": "Hollywood Insider", "FilmUrl": "https://www.imdb.com/title/tt8638066/?ref_=nm_flmg_slf_1", "Directors": [], "Writers": [], "Stars": ["Pritan Ambroase", "Tom Holland", "Margot Robbie"], "Genres": ["Talk-Show"], "ProductionCompanies": ["Hollywood Insider", "Concierge Content"], "PlotKeywords": ["entertainment", "non fiction"], "ReleaseDate": "17 May 2018", "Budget": 16000000}, {"CharacterName": "Self", "Year": "2020", "FilmTitle": "Ok! TV", "FilmUrl": "https://www.imdb.com/title/tt3503424/?ref_=nm_flmg_slf_2", "Directors": [], "Writers": [], "Stars": ["Sonia Isabelle", "Jaymes Vaughan", "Arthur Kade"], "Genres": ["News", "Talk-Show"], "ProductionCompanies": ["Unconventional Partners"], "PlotKeywords": ["celebrity", "stars", "non fiction"], "ReleaseDate": "9 September 2013", "RuntimeMinutes": 30}, {"CharacterName": "Self - Presenter", "Year": "2020", "FilmTitle": "EE British Academy Film Awards", "FilmUrl": "https://www.imdb.com/title/tt11338406/?ref_=nm_flmg_slf_3", "Directors": ["Matthew Amos"], "Writers": ["Sarah Morgan", "Shaun Pye"], "Stars": ["Jessie Buckley", "Margot Robbie", "Brad Pitt"], "Genres": ["News"], "ProductionCompanies": ["Whizz Kid Entertainment", "British Academy of Film and Television Arts (BAFTA)"], "PlotKeywords": ["tv special", "awards show"], "UserReviews": 2, "CriticReviews": 1, "ReleaseDate": "2 February 2020"}, {"CharacterName": "Self - Guest", "Year": "2018-2020", "FilmTitle": "The Graham Norton Show", "FilmUrl": "https://www.imdb.com/title/tt0924651/?ref_=nm_flmg_slf_4", "Directors": [], "Writers": [], "Stars": ["Graham Norton", "Ricky Gervais", "Judi Dench"], "Genres": ["Comedy", "Music", "Talk-Show"], "ProductionCompanies": ["So Television", "British Broadcasting Corporation (BBC)"], "PlotKeywords": ["actor name in series title", "four word series title", "opening monologue", "interview", "audience participation"], "UserReviews": 12, "CriticReviews": 1, "Popularity": 305, "ReleaseDate": "22 February 2007", "RuntimeMinutes": 60}, {"CharacterName": "Self - Guest", "Year": "2020", "FilmTitle": "Chicken Shop Date", "FilmUrl": "https://www.imdb.com/title/tt9662962/?ref_=nm_flmg_slf_5", "Directors": [], "Writers": [], "Stars": ["Amelia Dimoldenberg", "Charlie Cooper", "Ghetts"], "Genres": ["Comedy", "Talk-Show"], "ProductionCompanies": [], "PlotKeywords": ["non fiction"], "ReleaseDate": "24 March 2014"}, {"CharacterName": "Self", "Year": "2018-2019", "FilmTitle": "WGN Morning News", "FilmUrl": "https://www.imdb.com/title/tt5139360/?ref_=nm_flmg_slf_6", "Directors": [], "Writers": [], "Stars": ["Dean Richards", "Mike Toomey", "Robin Baumgarten"], "Genres": ["News"], "ProductionCompanies": ["WGN Chicago"], "PlotKeywords": ["chicago illinois", "non fiction"], "UserReviews": 2, "ReleaseDate": "6 September 1994"}, {"CharacterName": "Self - Guest", "Year": "2019", "FilmTitle": "IMDb on the Scene - Interviews", "FilmUrl": "https://www.imdb.com/title/tt8596744/?ref_=nm_flmg_slf_7", "Directors": [], "Writers": [], "Stars": ["Bret Federigan", "Alex Logan", "Albert Lawrence"], "Genres": ["Talk-Show"], "ProductionCompanies": ["IMDb Originals"], "PlotKeywords": ["cast", "non fiction"], "Popularity": 726, "ReleaseDate": "3 July 2018"}, {"CharacterName": "Self - Guest", "Year": "2019", "FilmTitle": "The Daily Show", "FilmUrl": "https://www.imdb.com/title/tt0115147/?ref_=nm_flmg_slf_8", "Directors": [], "Writers": [], "Stars": ["Jon Stewart", "Trevor Noah", "Stephen Colbert"], "Genres": ["Comedy", "News", "Talk-Show"], "ProductionCompanies": ["Ark Angel Entertainment", "Mad Cow Productions", "Comedy Central"], "PlotKeywords": ["interview", "1990s", "2000s", "2010s", "2020s"], "UserReviews": 156, "CriticReviews": 44, "Popularity": 451, "ReleaseDate": "22 July 1996", "RuntimeMinutes": 22}, {"CharacterName": "Self - Guest", "Year": "2018-2019", "FilmTitle": "The Late Show with Stephen Colbert", "FilmUrl": "https://www.imdb.com/title/tt3697842/?ref_=nm_flmg_slf_9", "Directors": [], "Writers": [], "Stars": ["Stephen Colbert", "Jonathan Batiste", "Stay Human"], "Genres": ["Comedy", "Talk-Show"], "ProductionCompanies": ["Spartina Productions", "CBS Television Studios"], "PlotKeywords": ["six word series title", "actor name in series title", "2020s", "woke", "anti trump media"], "UserReviews": 97, "CriticReviews": 16, "Popularity": 29, "ReleaseDate": "8 September 2015", "RuntimeMinutes": 41}, {"CharacterName": "Self - Guest", "Year": "2017-2019", "FilmTitle": "Today", "FilmUrl": "https://www.imdb.com/title/tt0044298/?ref_=nm_flmg_slf_10", "Directors": [], "Writers": [], "Stars": ["Savannah Guthrie", "Hoda Kotb", "Al Roker"], "Genres": ["News", "Talk-Show"], "ProductionCompanies": ["NBC News"], "PlotKeywords": ["weather", "one word title", "morning show", "non fiction"], "UserReviews": 16, "ReleaseDate": "14 January 1952", "RuntimeMinutes": 120}, {"CharacterName": "Self - Presenter", "Year": "2019", "FilmTitle": "BET Hip-Hop Awards", "FilmUrl": "https://www.imdb.com/title/tt10950998/?ref_=nm_flmg_slf_11", "Directors": ["Iren Brown", "Jonte"], "Writers": ["Mitchell Marchand", "Jesse Collins"], "Stars": ["Daniel Kaluuya", "Anderson .Paak", "Teyana Taylor"], "Genres": ["Music"], "ProductionCompanies": ["Jesse Collins Entertainment"], "PlotKeywords": ["tv special", "awards ceremony", "african american music", "music awards", "hip hop culture"], "ReleaseDate": "8 October 2019", "RuntimeMinutes": 150}, {"CharacterName": "Narrator", "Year": "2018", "FilmTitle": "Cities: Nature's New Wild", "FilmUrl": "https://www.imdb.com/title/tt9530156/?ref_=nm_flmg_slf_12", "Directors": [], "Writers": [], "Stars": ["Daniel Kaluuya", "Clint Penick"], "Genres": ["Documentary"], "ProductionCompanies": [], "PlotKeywords": ["tv mini series"], "UserReviews": 4, "ReleaseDate": "30 December 2018"}, {"CharacterName": "Self - Interviewee", "Year": "2018", "FilmTitle": "D\u00edas de cine", "FilmUrl": "https://www.imdb.com/title/tt0390699/?ref_=nm_flmg_slf_13", "Directors": [], "Writers": [], "Stars": ["Elena S. S\u00e1nchez", "Gerardo S\u00e1nchez", "Antonio Gasset"], "Genres": ["News"], "ProductionCompanies": ["Televisi\u00f3n Espa\u00f1ola (TVE)"], "PlotKeywords": ["cinema", "non fiction"], "RuntimeMinutes": 60}, {"CharacterName": "Self - Guest", "Year": "2018", "FilmTitle": "Jimmy Kimmel Live!", "FilmUrl": "https://www.imdb.com/title/tt0320037/?ref_=nm_flmg_slf_14", "Directors": [], "Writers": [], "Stars": ["Jimmy Kimmel", "Cleto and the Cletones", "Cleto Escobedo III"], "Genres": ["Comedy", "Music", "Talk-Show"], "ProductionCompanies": ["Jackhole Industries", "12:05 Productions", "ABC Studios"], "PlotKeywords": ["woke", "actor plays himself", "actor name in series title", "exclamation point in series title", "2000s"], "UserReviews": 60, "CriticReviews": 2, "Popularity": 326, "ReleaseDate": "26 January 2003", "RuntimeMinutes": 60}, {"CharacterName": "Self", "Year": "2018", "FilmTitle": "Saturday Night Live", "FilmUrl": "https://www.imdb.com/title/tt0072562/?ref_=nm_flmg_slf_15", "Directors": [], "Writers": [], "Stars": ["The Saturday Night Live Band", "Don Pardo", "Lenny Pickett"], "Genres": ["Comedy", "Music"], "ProductionCompanies": ["NBC Studios", "NBC Universal Television", "Broadway Video"], "PlotKeywords": ["20th century", "21st century", "1970s", "2000s", "2010s"], "UserReviews": 271, "CriticReviews": 10, "Popularity": 191, "ReleaseDate": "11 October 1975", "RuntimeMinutes": 90}, {"CharacterName": "Self", "Year": "2018", "FilmTitle": "Good Morning Britain", "FilmUrl": "https://www.imdb.com/title/tt3644198/?ref_=nm_flmg_slf_16", "Directors": [], "Writers": [], "Stars": ["Andi Peters", "Lorraine Kelly", "Susanna Reid"], "Genres": ["News", "Talk-Show"], "ProductionCompanies": ["ITV Studios"], "PlotKeywords": ["celebrity guest", "morning", "breakfast tv", "non fiction", "mainstream media"], "UserReviews": 7, "ReleaseDate": "28 April 2014", "RuntimeMinutes": 150}, {"CharacterName": "Self - Nominee", "Year": "2018", "FilmTitle": "The Oscars", "FilmUrl": "https://www.imdb.com/title/tt7235270/?ref_=nm_flmg_slf_17", "Directors": ["Glenn Weiss"], "Writers": ["Jon Macks", "Amberia Allen"], "Stars": ["Margot Robbie", "Brad Pitt", "Scarlett Johansson"], "Genres": ["Music"], "ProductionCompanies": ["Academy of Motion Picture Arts and Sciences (AMPAS)"], "PlotKeywords": ["awards show", "tv special", "2020s", "reference to 1917", "reference to 'joker' 2019"], "UserReviews": 14, "CriticReviews": 2, "ReleaseDate": "9 February 2020", "RuntimeMinutes": 170}, {"CharacterName": "Self", "Year": "2018", "FilmTitle": "The Oscars Opening Ceremony: Live from the Red Carpet", "FilmUrl": "https://www.imdb.com/title/tt8027544/?ref_=nm_flmg_slf_18", "Directors": ["Jeff Winn"], "Writers": [], "Stars": ["Mel Gibson", "Dwayne Johnson", "Nicole Kidman"], "Genres": [], "ProductionCompanies": ["Lincoln Square Productions"], "PlotKeywords": ["tv special", "red carpet"], "ReleaseDate": "26 February 2017", "Budget": 1000000}, {"CharacterName": "Self", "Year": "2018", "FilmTitle": "Essence 11th Annual Black Women in Hollywood Awards", "FilmUrl": "https://www.imdb.com/title/tt8358926/?ref_=nm_flmg_slf_19", "Directors": [], "Writers": ["Regina R. Robertson"], "Stars": ["Yvonne Orji", "Tiffany Haddish", "Danai Gurira"], "Genres": ["Talk-Show"], "ProductionCompanies": [], "PlotKeywords": ["awards ceremony", "african american", "hollywood", "black culture", "tv special"], "ReleaseDate": "3 March 2018", "RuntimeMinutes": 90}, {"CharacterName": "Self - Winner", "Year": "2018", "FilmTitle": "The EE British Academy Film Awards", "FilmUrl": "https://www.imdb.com/title/tt7866928/?ref_=nm_flmg_slf_20", "Directors": ["Matthew Amos"], "Writers": [], "Stars": ["Stephen Fry", "Amy Adams", "Patricia Arquette"], "Genres": ["News"], "ProductionCompanies": ["Whizz Kid Entertainment", "British Academy of Film and Television Arts (BAFTA)", "British Broadcasting Corporation (BBC)"], "PlotKeywords": ["awards show", "tv special"], "UserReviews": 1, "ReleaseDate": "8 February 2015"}, {"CharacterName": "Self", "Year": "2018", "FilmTitle": "Made in Hollywood", "FilmUrl": "https://www.imdb.com/title/tt0911896/?ref_=nm_flmg_slf_21", "Directors": [], "Writers": [], "Stars": ["Kylie Erica Mar", "Julie L. Harkness", "Patrick Stinson"], "Genres": ["Talk-Show"], "ProductionCompanies": ["Connection III Entertainment"], "PlotKeywords": ["three word title", "guest", "celebrity"], "UserReviews": 1, "ReleaseDate": "30 September 2005"}, {"CharacterName": "Self - Black Panther / Self / Self - SAG Awards", "Year": "2018", "FilmTitle": "Entertainment Tonight Canada", "FilmUrl": "https://www.imdb.com/title/tt0482346/?ref_=nm_flmg_slf_22", "Directors": [], "Writers": [], "Stars": ["Carlos Bustamante", "Cheryl Hickey", "Sangita Patel"], "Genres": ["Biography", "Family", "News", "Reality-TV"], "ProductionCompanies": ["Corus Entertainment"], "PlotKeywords": ["country name in title", "three word title", "show business", "promotional", "music industry"], "UserReviews": 2, "ReleaseDate": "12 September 2005", "RuntimeMinutes": 30}, {"CharacterName": "Self", "Year": "2018", "FilmTitle": "Last Week", "FilmUrl": "https://www.imdb.com/title/tt8527880/?ref_=nm_flmg_slf_23", "Directors": [], "Writers": [], "Stars": ["Thomas Ridgewell", "Elliot Gough", "Eddie Bowley"], "Genres": ["Comedy", "Reality-TV"], "ProductionCompanies": [], "PlotKeywords": ["comedian", "non fiction"], "ReleaseDate": "5 April 2016", "RuntimeMinutes": 30}, {"CharacterName": "Self - Guest", "Year": "2008-2018", "FilmTitle": "This Morning", "FilmUrl": "https://www.imdb.com/title/tt0181261/?ref_=nm_flmg_slf_24", "Directors": [], "Writers": [], "Stars": ["Phillip Schofield", "Holly Willoughby", "Ruth Langsford"], "Genres": ["Comedy", "News", "Talk-Show"], "ProductionCompanies": ["Granada Television"], "PlotKeywords": ["fashion", "interview", "cookery", "lifestyle", "celebrity interview"], "UserReviews": 7, "ReleaseDate": "3 October 1988", "RuntimeMinutes": 120}, {"CharacterName": "Self - Actor", "Year": "2018", "FilmTitle": "News at Ten", "FilmUrl": "https://www.imdb.com/title/tt0229912/?ref_=nm_flmg_slf_25", "Directors": [], "Writers": [], "Stars": ["Lucy Verasamy", "Tom Bradby", "Alex Beresford"], "Genres": ["News"], "ProductionCompanies": ["Independent Television News (ITN)"], "PlotKeywords": ["long running tv", "british politics", "2010s", "2000s", "1990s"], "ReleaseDate": "3 July 1967"}, {"CharacterName": "Self - Guest", "Year": "2018", "FilmTitle": "The IMDb Show", "FilmUrl": "https://www.imdb.com/title/tt7549864/?ref_=nm_flmg_slf_26", "Directors": [], "Writers": [], "Stars": ["Tim Kash", "Kerri Doherty", "Alex Logan"], "Genres": ["Talk-Show"], "ProductionCompanies": ["IMDb Originals", "IMDb", "INE Entertainment"], "PlotKeywords": ["celebrity", "reference to imdb", "entertainment", "discussion", "interview"], "UserReviews": 23, "CriticReviews": 1, "ReleaseDate": "16 November 2017", "RuntimeMinutes": 13}, {"CharacterName": "Self - Nominee &amp; Presenter", "Year": "2018", "FilmTitle": "24th Annual Screen Actors Guild Awards", "FilmUrl": "https://www.imdb.com/title/tt8053828/?ref_=nm_flmg_slf_27", "Directors": ["Alan Carter"], "Writers": ["Beth Armogida", "Dave Boone"], "Stars": ["Anthony Anderson", "Rosanna Arquette", "Jonathan Banks"], "Genres": ["Comedy", "Music"], "ProductionCompanies": ["Avalon Harbor Entertainment"], "PlotKeywords": ["tv special", "awards show"], "UserReviews": 1, "ReleaseDate": "21 January 2018"}, {"CharacterName": "Self", "Year": "2018", "FilmTitle": "49th NAACP Image Awards", "FilmUrl": "https://www.imdb.com/title/tt7913148/?ref_=nm_flmg_slf_28", "Directors": ["Tony McCuin"], "Writers": ["Jon Macks"], "Stars": ["Anthony Anderson", "Tai Beauchamp", "Halle Berry"], "Genres": ["News", "Reality-TV"], "ProductionCompanies": ["Hudlin Entertainment", "Syndrome Studio", "The Gurin Company"], "PlotKeywords": ["awards show", "african american", "entertainment", "persons of color", "black culture"], "ReleaseDate": "15 January 2018", "RuntimeMinutes": 180}, {"CharacterName": "Self", "Year": "2018", "FilmTitle": "49th NAACP Image Awards Red Carpet", "FilmUrl": "https://www.imdb.com/title/tt7919294/?ref_=nm_flmg_slf_29", "Directors": [], "Writers": [], "Stars": ["Terrence Jenkins", "Tamika Ray", "Tanika Ray"], "Genres": ["History"], "ProductionCompanies": ["TV One", "Syndrome Studio"], "PlotKeywords": ["celebrity", "red carpet", "awards", "tv special"], "ReleaseDate": "15 January 2018", "RuntimeMinutes": 60}, {"CharacterName": "Self - Nominee", "Year": "2018", "FilmTitle": "75th Golden Globe Awards", "FilmUrl": "https://www.imdb.com/title/tt6635044/?ref_=nm_flmg_slf_30", "Directors": ["Louis J. Horvitz"], "Writers": ["Barry Adelman", "Michael Shoemaker"], "Stars": ["Robert Pattinson", "Timoth\u00e9e Chalamet", "Christopher Nolan"], "Genres": ["Comedy", "News"], "ProductionCompanies": ["Dick Clark Productions", "Hollywood Foreign Press Association (HFPA)"], "PlotKeywords": ["awards show", "reference to imdb", "reference to harvey weinstein", "reference to kevin spacey", "reference to woody allen"], "UserReviews": 6, "CriticReviews": 5, "ReleaseDate": "7 January 2018"}, {"CharacterName": "Self", "Year": "2018", "FilmTitle": "Variety Studio: Actors on Actors", "FilmUrl": "https://www.imdb.com/title/tt4267324/?ref_=nm_flmg_slf_31", "Directors": [], "Writers": [], "Stars": ["Jenelle Riley", "Michael Keaton", "Benicio Del Toro"], "Genres": ["Talk-Show"], "ProductionCompanies": ["Lodger Films", "PBS SoCal"], "PlotKeywords": ["non fiction"], "ReleaseDate": "21 December 2014"}, {"CharacterName": "Self", "Year": "2017", "FilmTitle": "Q&A Discussion with Writer/Director Jordan Peele and the Cast of 'Get Out'", "FilmUrl": "https://www.imdb.com/title/tt7045536/?ref_=nm_flmg_slf_32", "Directors": [], "Writers": [], "Stars": ["Daniel Kaluuya", "Jordan Peele", "Allison Williams"], "Genres": ["Documentary", "Short"], "ProductionCompanies": [], "PlotKeywords": ["dvd extra"], "ReleaseDate": "23 May 2017", "RuntimeMinutes": 5}, {"CharacterName": "Self", "Year": "2017", "FilmTitle": "Unveiling the Horror of 'Get Out'", "FilmUrl": "https://www.imdb.com/title/tt7045554/?ref_=nm_flmg_slf_33", "Directors": [], "Writers": [], "Stars": ["Jordan Peele", "Sean McKittrick", "Jason Blum"], "Genres": ["Documentary", "Short"], "ProductionCompanies": [], "PlotKeywords": ["making of", "dvd extra"], "ReleaseDate": "23 May 2017", "RuntimeMinutes": 9}, {"CharacterName": "Self - Winner", "Year": "2017", "FilmTitle": "2017 MTV Movie & TV Awards", "FilmUrl": "https://www.imdb.com/title/tt6998250/?ref_=nm_flmg_slf_34", "Directors": ["Joe DeMaio", "Dan Opsal"], "Writers": ["Scotty Landes", "Tom Reed"], "Stars": ["Adam Devine", "Ajiona Alexus", "Blake Anderson"], "Genres": ["Music"], "ProductionCompanies": ["Casey Patterson Entertainment", "MTV Networks"], "PlotKeywords": ["awards show", "tv special"], "UserReviews": 1, "ReleaseDate": "7 May 2017"}, {"CharacterName": "Self", "Year": "2017", "FilmTitle": "Access Daily", "FilmUrl": "https://www.imdb.com/title/tt1746642/?ref_=nm_flmg_slf_35", "Directors": [], "Writers": [], "Stars": ["Kit Hoover", "Natalie Morales", "Billy Bush"], "Genres": ["Talk-Show"], "ProductionCompanies": [], "PlotKeywords": ["live", "entertainment news", "entertainment", "hollywood", "media"], "UserReviews": 6, "ReleaseDate": "13 September 2010", "RuntimeMinutes": 60}, {"CharacterName": "Self", "Year": "2017", "FilmTitle": "Allison's Edge", "FilmUrl": "https://www.imdb.com/title/tt6691550/?ref_=nm_flmg_slf_36", "Directors": ["Vincent Peone"], "Writers": [], "Stars": ["Andy Cohen", "Lena Dunham", "Daniel Kaluuya"], "Genres": ["Short", "Comedy"], "ProductionCompanies": ["Big Block Productions"], "PlotKeywords": [], "ReleaseDate": "14 February 2017", "Budget": 100, "RuntimeMinutes": 3}, {"CharacterName": "Self / Reggie Wayne", "Year": "2016", "FilmTitle": "Stepping Into Darkness: The Visual Design of Sicario", "FilmUrl": "https://www.imdb.com/title/tt5351508/?ref_=nm_flmg_slf_37", "Directors": [], "Writers": [], "Stars": ["Denis Villeneuve", "Taylor Sheridan", "Roger Deakins"], "Genres": ["Documentary", "Short"], "ProductionCompanies": ["Rolling Thunder Productions"], "PlotKeywords": ["dvd extra"], "ReleaseDate": "5 January 2016", "RuntimeMinutes": 16}, {"CharacterName": "Self", "Year": "2008", "FilmTitle": "How TV Changed Britain", "FilmUrl": "https://www.imdb.com/title/tt1242490/?ref_=nm_flmg_slf_38", "Directors": [], "Writers": [], "Stars": ["Stephen Mangan", "Dominic Sandbrook", "Peter Bazalgette"], "Genres": ["Documentary"], "ProductionCompanies": ["Silver River Productions", "Channel 4 Television Corporation"], "PlotKeywords": ["television", "interview", "cultural impact"], "UserReviews": 1, "CriticReviews": 1, "ReleaseDate": "1 June 2008", "RuntimeMinutes": 48}, {"CharacterName": "Chris Washington", "Year": "2019", "FilmTitle": "The Movies", "FilmUrl": "https://www.imdb.com/title/tt10468676/?ref_=nm_flmg_arf_1", "Directors": [], "Writers": [], "Stars": ["Paul Thomas Anderson", "Brad Bird", "Alonso Duralde"], "Genres": ["Documentary"], "ProductionCompanies": ["CNN", "HBO Films"], "PlotKeywords": [], "UserReviews": 21, "ReleaseDate": "7 July 2019", "RuntimeMinutes": 120}]}